LICENSE
setup.py
cmhi/__init__.py
cmhi/cmhi.py
cmhi.egg-info/PKG-INFO
cmhi.egg-info/SOURCES.txt
cmhi.egg-info/dependency_links.txt
cmhi.egg-info/requires.txt
cmhi.egg-info/top_level.txt